{
  "﻿WordPress Unique ID": "1389",
  "Drupal Unique ID": "5833",
  "URL": "/hermannk",
  "Directory": "H",
  "Title": "Hermann, Karl Friedrich",
  "Full Name": "Hermann, Karl Friedrich",
  "Birth Year": "1804",
  "Death Year": "1855",
  "Home Country": "Germany",
  "Gender": "male",
  "Subject Area": "Ancient Greek (culture or style)|Classical",
  "Career": "educators",
  "Overview": "<p>University of Heidelberg classical professor, taught Greek art. He was succeeded by <a href=\"/starkk\">Karl Bernhard Stark</a>, who was named the first chair in archaeology.</p>",
  "Selected Bibliography": "updated by Stark, Karl B. and Bähr, Johann Christian Felix. <em>Lehrbuch der griechischen Antiquitäten</em>. 3 vols. Heidelberg, J.C.B. Mohr, 1855.",
  "Date Last Modified": "11/8/2023 22:48"
}