{
  "﻿WordPress Unique ID": "1199",
  "Drupal Unique ID": "5642",
  "URL": "/gerstenbergk",
  "Directory": "G",
  "Title": "Gerstenberg, Kurt",
  "Full Name": "Gerstenberg, Kurt",
  "Birth Year": "1886",
  "Death Year": "1968",
  "Place Born": "Chemnitz, Saxony, Germany",
  "Place Died": "Würzburg, Bavaria, Germany",
  "Home Country": "Germany",
  "Gender": "male",
  "Sources": "<em>Metzler Kunsthistoriker Lexikon: zweihundert Porträts deutschsprachiger Autoren aus vier Jahrhunderten</em>. Stuttgart: Metzler, 1999, pp. 115-117.",
  "Date Last Modified": "11/8/2023 22:48"
}