{
  "﻿WordPress Unique ID": "1368",
  "Drupal Unique ID": "5812",
  "URL": "/heineckenc",
  "Directory": "H",
  "Title": "Heinecken, Carl Heinrich von",
  "Full Name": "Heinecken, Carl Heinrich von",
  "Other Names": "Carl Heinrich von Heineken",
  "Birth Year": "1701",
  "Death Year": "1791",
  "Place Born": "Lübeck, Schleswig-Holstein, Germany",
  "Place Died": "Aldöbern, Germany",
  "Home Country": "Germany",
  "Gender": "male",
  "Sources": "<em>Metzler Kunsthistoriker Lexikon: zweihundert Porträts deutschsprachiger Autoren aus vier Jahrhunderten</em>. Stuttgart: Metzler, 1999, pp. 163-4.",
  "Date Last Modified": "11/8/2023 22:48"
}