{
  "﻿WordPress Unique ID": "1686",
  "Drupal Unique ID": "6132",
  "URL": "/lazarevv",
  "Directory": "L",
  "Title": "Lazarev, Viktor Mikitich",
  "Full Name": "Lazarev, Viktor Mikitich",
  "Birth Year": "1896",
  "Death Year": "1976",
  "Home Country": "Russia",
  "Gender": "male",
  "Subject Area": "Byzantine (culture or style)|iconography|Medieval (European)",
  "Overview": "<p>Byzantine iconography; student of <a href=\"/ainalovd\">Dmitrii Vlas'evich Ainalov III</a></p>",
  "Sources": "KRG, 61 mentioned",
  "Date Last Modified": "11/8/2023 22:49"
}