{
  "﻿WordPress Unique ID": "2004",
  "Drupal Unique ID": "6451",
  "URL": "/okladnikova",
  "Directory": "O",
  "Title": "Okladnikov, A. P.",
  "Full Name": "Okladnikov, A. P.",
  "Other Names": "Aleksei Pavlovich Okladnikov",
  "Birth Year": "1908",
  "Death Year": "1981",
  "Place Born": "Konstantinovshchina, Irkutsk Oblast, Russia",
  "Place Died": "Moscow, Russia",
  "Home Country": "Russia",
  "Gender": "male",
  "Subject Area": "archaeology|prehistoric",
  "Overview": "<p>Archaeologist and historian of prehistoric art and culture. For twenty-three years, Okladnikov served as a staff member of the USSR Academy of Sciences' Institute of Archaeology in Leningrad. His research concentrated on the art of the Bronze Age in the Baikal region, and the monuments of the Neolithic Age. In 1961, Okladinov was appointed head of the humanities research department of the Institute of Economics in the USSR Academy of Science's Siberian division. One year later, he became a professor and chair of the history department at Novosibirsk University. In 1968, Okladinov was received the title of academician by the USSR Academy of Sciences.</p>",
  "Selected Bibliography": "<em>Keramika drevnego poseleniia Kondon : Priamur'e</em>. Novosibirsk: Izd-vo \"Nauka,\" Sibirskoe otd-nie, 1984; <em>Ancient Art of the Amur Region: Ancient Art of the Russian Far East</em>. New York: Abrams, 1981; and A. I Mazin. Pisanitsy reki Olekmy i Verkhnego Priamur'ia. AN SSSR, Sib. otd-nie, In-t istorii, filologii i filosofii. Novosibirsk: Nauka, Sib. otd-nie, 1976.",
  "Sources": "<em>The Dictionary of Art</em>",
  "Contributors": "LaNitra Michele Walker",
  "Date Last Modified": "11/8/2023 22:51"
}