{
  "﻿WordPress Unique ID": "2186",
  "Drupal Unique ID": "6635",
  "URL": "/reichs",
  "Directory": "R",
  "Title": "Reich, Sheldon",
  "Full Name": "Reich, Sheldon",
  "Birth Year": "unknown",
  "Death Year": "unknown",
  "Gender": "male",
  "Subject Area": "catalogues raisonnés|stylistic analysis",
  "Overview": "<p>The authoritative study of Marin is Sheldon Reich's <em>John Marin: A Stylistic Analysis and Catalogue Raisonne</em> (2 vols., 1970).</p>",
  "Date Last Modified": "11/8/2023 22:51"
}